pyseekdb-1.1.0.dist-info/METADATA
pyseekdb-1.1.0.dist-info/WHEEL
pyseekdb-1.1.0.dist-info/entry_points.txt
pyseekdb-1.1.0.dist-info/licenses/LICENSE
pyseekdb/__init__.py
pyseekdb/client/__init__.py
pyseekdb/client/admin_client.py
pyseekdb/client/base_connection.py
pyseekdb/client/client_base.py
pyseekdb/client/client_seekdb_embedded.py
pyseekdb/client/client_seekdb_server.py
pyseekdb/client/collection.py
pyseekdb/client/configuration.py
pyseekdb/client/database.py
pyseekdb/client/embedding_function.py
pyseekdb/client/filters.py
pyseekdb/client/meta_info.py
pyseekdb/client/sql_utils.py
pyseekdb/client/version.py
pyseekdb/utils/embedding_functions/__init__.py
pyseekdb/utils/embedding_functions/amazon_bedrock_embedding_function.py
pyseekdb/utils/embedding_functions/cohere_embedding_function.py
pyseekdb/utils/embedding_functions/google_vertex_embedding_function.py
pyseekdb/utils/embedding_functions/jina_embedding_function.py
pyseekdb/utils/embedding_functions/litellm_base_embedding_function.py
pyseekdb/utils/embedding_functions/ollama_embedding_function.py
pyseekdb/utils/embedding_functions/openai_base_embedding_function.py
pyseekdb/utils/embedding_functions/openai_embedding_function.py
pyseekdb/utils/embedding_functions/qwen_embedding_function.py
pyseekdb/utils/embedding_functions/sentence_transformer_embedding_function.py
pyseekdb/utils/embedding_functions/siliconflow_embedding_function.py
pyseekdb/utils/embedding_functions/tencent_hunyuan_embedding_function.py
pyseekdb/utils/embedding_functions/voyageai_embedding_function.py
pyseekdb-1.1.0.dist-info/RECORD
