Metadata-Version: 2.1
Name: pyseekdb
Version: 1.1.0
Summary: A unified Python client for seekdb that supports embedded, server, and OceanBase.
Author-Email: OceanBase <open_oceanbase@oceanbase.com>
License: Apache-2.0
Classifier: Development Status :: 4 - Beta
Project-URL: Homepage, https://github.com/oceanbase/pyseekdb/
Project-URL: Repository, https://github.com/oceanbase/pyseekdb/
Project-URL: Bug Tracker, https://github.com/oceanbase/pyseekdb/issues
Requires-Python: <3.14,>=3.11
Requires-Dist: pymysql>=1.1.1
Requires-Dist: pylibseekdb; sys_platform == "linux" or (sys_platform == "darwin" and platform_machine == "arm64")
Requires-Dist: onnxruntime>=1.19.0
Requires-Dist: tokenizers>=0.15.0
Requires-Dist: httpx
Requires-Dist: tqdm
Requires-Dist: tenacity
Requires-Dist: numpy>=1.26
